{"nom":"Machin","today":"20/11/2016"}

Localisation :
{"salle":"s1","rayon":"r1"}
{"salle":"s1","rayon":"r2"}
{"salle":"s1","rayon":"r3"}
{"salle":"s2","rayon":"r1"}
{"salle":"s2","rayon":"r2"}
{"salle":"s2","rayon":"r3"}
{"salle":"s1","rayon":"r1"}

Document :
Audio :
{"code":"a1","titre":"a1","auteur":"a1","annee":"2016","empruntable":"false","emprunte":"false","nbEmprunts":0,"classification":"a1","loc":{"salle":"s1","rayon":"r1"},"genre":{"ordinal":1}}
{"code":"a2","titre":"a2","auteur":"a2","annee":"2016","empruntable":"false","emprunte":"false","nbEmprunts":0,"classification":"a2","loc":{"salle":"s1","rayon":"r1"},"genre":{"ordinal":1}}
Livre :
{"code":"l1","titre":"l1","auteur":"l1","annee":"2016","empruntable":"false","emprunte":"false","nbEmprunts":0,"nbPages":1,"loc":{"salle":"s1","rayon":"r3"},"genre":{"ordinal":2}}
{"code":"l2","titre":"l2","auteur":"l2","annee":"2016","empruntable":"false","emprunte":"false","nbEmprunts":0,"nbPages":2,"loc":{"salle":"s2","rayon":"r1"},"genre":{"ordinal":2}}
Video :
{"code":"v1","titre":"v1","auteur":"v1","annee":"2016","empruntable":"false","emprunte":"false","nbEmprunts":0,"dureeFilm":1,"mentionsLegales":"v1","loc":{"salle":"s2","rayon":"r2"},"genre":{"ordinal":3}}
{"code":"v2","titre":"v2","auteur":"v2","annee":"2016","empruntable":"false","emprunte":"false","nbEmprunts":0,"dureeFilm":2,"mentionsLegales":"v2","loc":{"salle":"s2","rayon":"r3"},"genre":{"ordinal":3}}

Client :
{"categorie":{"ordinal":1,"actif":"false"},"nom":"a","prenom":"a","adresse":"a","dateInscription":"20/11/2016","dateRenouvellement":"20/11/2016","nbEmpruntsEffectues":0,"nbEmpruntsDepasses":0,"nbEmpruntsEnCours":0,"codeReduction":0,"matricule":"PA6721"}
{"categorie":{"ordinal":1,"actif":"false"},"nom":"b","prenom":"b","adresse":"b","dateInscription":"20/11/2016","dateRenouvellement":"20/11/2016","nbEmpruntsEffectues":0,"nbEmpruntsDepasses":0,"nbEmpruntsEnCours":0,"codeReduction":0,"matricule":"PA8306"}

Fiche Emprunt :
{"dateEmprunt":"20/11/2016","dateLimite":"20/11/2016","dateRappel":"19/11/2016","depasse":"false","tarif":"0.0","codeClient":"PA6721","codeDoc":"a1"}
{"dateEmprunt":"20/11/2016","dateLimite":"20/11/2016","dateRappel":"19/11/2016","depasse":"false","tarif":"0.0","codeClient":"PA8306","codeDoc":"v1"}

